[
   {
      "Player": "Alfonzo McKinnie",
      "Team": "Golden State Warriors",
      "Season": "2018-19",
      "Salary": "$1,349,383"
   },
   {
      "Player": "Jonas Jerebko",
      "Team": "Golden State Warriors",
      "Season": "2018-19",
      "Salary": "$2,165,481"
   },
   {
      "Player": "Kevon Looney",
      "Team": "Golden State Warriors",
      "Season": "2018-19",
      "Salary": "$1,567,007"
   },
   {
      "Player": "Kevin Durant",
      "Team": "Golden State Warriors",
      "Season": "2018-19",
      "Salary": "$30,000,000"
   },
   {
      "Player": "DeMarcus Cousins",
      "Team": "Golden State Warriors",
      "Season": "2018-19",
      "Salary": "$5,337,000"
   },
   {
      "Player": "Jacob Evans",
      "Team": "Golden State Warriors",
      "Season": "2018-19",
      "Salary": "$1,644,240"
   },
   {
      "Player": "Quinn Cook",
      "Team": "Golden State Warriors",
      "Season": "2018-19",
      "Salary": "$1,544,951"
   },
   {
      "Player": "Shaun Livingston",
      "Team": "Golden State Warriors",
      "Season": "2018-19",
      "Salary": "$8,307,692"
   },
   {
      "Player": "Andre Iguodala",
      "Team": "Golden State Warriors",
      "Season": "2018-19",
      "Salary": "$16,000,000"
   },
   {
      "Player": "Stephen Curry",
      "Team": "Golden State Warriors",
      "Season": "2018-19",
      "Salary": "$37,457,154"
   },
   {
      "Player": "Jordan Bell",
      "Team": "Golden State Warriors",
      "Season": "2018-19",
      "Salary": "$1,378,252"
   },
   {
      "Player": "Damian Jones",
      "Team": "Golden State Warriors",
      "Season": "2018-19",
      "Salary": "$1,544,951"
   },
   {
      "Player": "Draymond Green",
      "Team": "Golden State Warriors",
      "Season": "2018-19",
      "Salary": "$17,469,565"
   },
   {
      "Player": "Klay Thompson",
      "Team": "Golden State Warriors",
      "Season": "2018-19",
      "Salary": "$18,988,725"
   }
]