[
   {
      "Player": "Wesley Matthews",
      "Team": "Indiana Pacers",
      "Season": "2018-19",
      "Salary": "$18,622,514"
   },
   {
      "Player": "Davon Reed",
      "Team": "Indiana Pacers",
      "Season": "2018-19",
      "Salary": "$1,378,242"
   },
   {
      "Player": "Alize Johnson",
      "Team": "Indiana Pacers",
      "Season": "2018-19",
      "Salary": "$838,464"
   },
   {
      "Player": "Kyle O'Quinn",
      "Team": "Indiana Pacers",
      "Season": "2018-19",
      "Salary": "$4,449,000"
   },
   {
      "Player": "Doug McDermott",
      "Team": "Indiana Pacers",
      "Season": "2018-19",
      "Salary": "$7,333,334"
   },
   {
      "Player": "Tyreke Evans",
      "Team": "Indiana Pacers",
      "Season": "2018-19",
      "Salary": "$12,400,000"
   },
   {
      "Player": "Aaron Holiday",
      "Team": "Indiana Pacers",
      "Season": "2018-19",
      "Salary": "$1,911,960"
   },
   {
      "Player": "Darren Collison",
      "Team": "Indiana Pacers",
      "Season": "2018-19",
      "Salary": "$10,000,000"
   },
   {
      "Player": "Bojan Bogdanovic",
      "Team": "Indiana Pacers",
      "Season": "2018-19",
      "Salary": "$10,500,000"
   },
   {
      "Player": "T.J. Leaf",
      "Team": "Indiana Pacers",
      "Season": "2018-19",
      "Salary": "$2,407,560"
   },
   {
      "Player": "Domantas Sabonis",
      "Team": "Indiana Pacers",
      "Season": "2018-19",
      "Salary": "$2,659,800"
   },
   {
      "Player": "Cory Joseph",
      "Team": "Indiana Pacers",
      "Season": "2018-19",
      "Salary": "$7,945,000"
   },
   {
      "Player": "Thaddeus Young",
      "Team": "Indiana Pacers",
      "Season": "2018-19",
      "Salary": "$13,764,045"
   },
   {
      "Player": "Myles Turner",
      "Team": "Indiana Pacers",
      "Season": "2018-19",
      "Salary": "$3,410,284"
   },
   {
      "Player": "Victor Oladipo",
      "Team": "Indiana Pacers",
      "Season": "2018-19",
      "Salary": "$21,000,000"
   }
]