[
   {
      "Player": "Bruno Caboclo",
      "Team": "Memphis Grizzlies",
      "Season": "2018-19",
      "Salary": "$487,000"
   },
   {
      "Player": "Joakim Noah",
      "Team": "Memphis Grizzlies",
      "Season": "2018-19",
      "Salary": "$18,530,000"
   },
   {
      "Player": "Jevon Carter",
      "Team": "Memphis Grizzlies",
      "Season": "2018-19",
      "Salary": "$838,464"
   },
   {
      "Player": "Kyle Anderson",
      "Team": "Memphis Grizzlies",
      "Season": "2018-19",
      "Salary": "$8,641,000"
   },
   {
      "Player": "Avery Bradley",
      "Team": "Memphis Grizzlies",
      "Season": "2018-19",
      "Salary": "$12,000,000"
   },
   {
      "Player": "Jaren Jackson Jr.",
      "Team": "Memphis Grizzlies",
      "Season": "2018-19",
      "Salary": "$5,915,040"
   },
   {
      "Player": "Ivan Rabb",
      "Team": "Memphis Grizzlies",
      "Season": "2018-19",
      "Salary": "$1,378,242"
   },
   {
      "Player": "Dillon Brooks",
      "Team": "Memphis Grizzlies",
      "Season": "2018-19",
      "Salary": "$1,378,242"
   },
   {
      "Player": "C.J. Miles",
      "Team": "Memphis Grizzlies",
      "Season": "2018-19",
      "Salary": "$8,333,333"
   },
   {
      "Player": "Tyler Dorsey",
      "Team": "Memphis Grizzlies",
      "Season": "2018-19",
      "Salary": "$1,378,242"
   },
   {
      "Player": "Justin Holiday",
      "Team": "Memphis Grizzlies",
      "Season": "2018-19",
      "Salary": "$4,384,616"
   },
   {
      "Player": "Mike Conley",
      "Team": "Memphis Grizzlies",
      "Season": "2018-19",
      "Salary": "$30,521,116"
   },
   {
      "Player": "Chandler Parsons",
      "Team": "Memphis Grizzlies",
      "Season": "2018-19",
      "Salary": "$24,107,258"
   },
   {
      "Player": "Delon Wright",
      "Team": "Memphis Grizzlies",
      "Season": "2018-19",
      "Salary": "$2,536,898"
   },
   {
      "Player": "Jonas Valanciunas",
      "Team": "Memphis Grizzlies",
      "Season": "2018-19",
      "Salary": "$16,539,326"
   }
]